datasources_lib/__init__.py
datasources_lib/base.py
datasources_lib/config.py
datasources_lib/exceptions.py
datasources_lib/pool.py
datasources_lib/opcua/__init__.py
datasources_lib/opcua/client.py
datasources_lib-0.1.0.dist-info/licenses/LICENSE
datasources_lib-0.1.0.dist-info/METADATA
datasources_lib-0.1.0.dist-info/WHEEL
datasources_lib-0.1.0.dist-info/top_level.txt
datasources_lib-0.1.0.dist-info/RECORD
